bcps/__init__.py
bcps/__main__.py
bcps/py.typed
bcps/cli/__init__.py
bcps/cli/color.py
bcps/cli/dialog_creator.py
bcps/cli/feature_handler.py
bcps/cli/file_dialog.py
bcps/cli/main.py
bcps/cli/save_management.py
bcps/cli/server_cli.py
bcps/cli/edits/__init__.py
bcps/cli/edits/aku_realm.py
bcps/cli/edits/basic_items.py
bcps/cli/edits/cat_editor.py
bcps/cli/edits/clear_tutorial.py
bcps/cli/edits/enemy_editor.py
bcps/cli/edits/fixes.py
bcps/cli/edits/map.py
bcps/cli/edits/rare_ticket_trade.py
bcps/core/__init__.py
bcps/core/country_code.py
bcps/core/crypto.py
bcps/core/game_version.py
bcps/core/locale_handler.py
bcps/core/log.py
bcps/core/max_value_helper.py
bcps/core/theme_handler.py
bcps/core/game/__init__.py
bcps/core/game/localizable.py
bcps/core/game/battle/__init__.py
bcps/core/game/battle/battle_items.py
bcps/core/game/battle/cleared_slots.py
bcps/core/game/battle/enemy.py
bcps/core/game/battle/slots.py
bcps/core/game/catbase/__init__.py
bcps/core/game/catbase/beacon_base.py
bcps/core/game/catbase/cat.py
bcps/core/game/catbase/drop_chara.py
bcps/core/game/catbase/gatya.py
bcps/core/game/catbase/gatya_item.py
bcps/core/game/catbase/item_pack.py
bcps/core/game/catbase/login_bonuses.py
bcps/core/game/catbase/matatabi.py
bcps/core/game/catbase/medals.py
bcps/core/game/catbase/mission.py
bcps/core/game/catbase/my_sale.py
bcps/core/game/catbase/nyanko_club.py
bcps/core/game/catbase/officer_pass.py
bcps/core/game/catbase/playtime.py
bcps/core/game/catbase/powerup.py
bcps/core/game/catbase/scheme_items.py
bcps/core/game/catbase/special_skill.py
bcps/core/game/catbase/stamp.py
bcps/core/game/catbase/talent_orbs.py
bcps/core/game/catbase/unlock_popups.py
bcps/core/game/catbase/upgrade.py
bcps/core/game/catbase/user_rank_rewards.py
bcps/core/game/gamoto/__init__.py
bcps/core/game/gamoto/base_materials.py
bcps/core/game/gamoto/cat_shrine.py
bcps/core/game/gamoto/catamins.py
bcps/core/game/gamoto/gamatoto.py
bcps/core/game/gamoto/ototo.py
bcps/core/game/map/__init__.py
bcpulsekor-3.2.1b2.dist-info/METADATA
bcpulsekor-3.2.1b2.dist-info/WHEEL
bcpulsekor-3.2.1b2.dist-info/entry_points.txt
bcpulsekor-3.2.1b2.dist-info/top_level.txt
bcpulsekor-3.2.1b2.dist-info/RECORD
