Metadata-Version: 2.4
Name: bcpulseKOR
Version: 3.2.1b2
Summary: A save file editor for The Battle Cats
Author: fieryhenry
License: GPL-3.0-or-later License
Project-URL: Homepage, https://github.com/fieryhenry/BCSFE-Python
Project-URL: Repository, https://github.com/fieryhenry/BCSFE-Python
Project-URL: Issues, https://github.com/fieryhenry/BCSFE-Python/issues
Project-URL: Changelog, https://github.com/fieryhenry/BCSFE-Python/blob/master/CHANGELOG.md
Keywords: battle cats,save editor,hacking
Classifier: Development Status :: 4 - Beta
Classifier: Intended Audience :: End Users/Desktop
Classifier: Topic :: Utilities
Classifier: Programming Language :: Python :: 3
Classifier: Programming Language :: Python :: 3.9
Classifier: License :: OSI Approved :: GNU General Public License v3 or later (GPLv3+)
Classifier: Operating System :: OS Independent
Requires-Python: >=3.9
Requires-Dist: aenum
Requires-Dist: colored==1.4.4
Requires-Dist: pyjwt
Requires-Dist: requests
Requires-Dist: pyyaml
Requires-Dist: beautifulsoup4
